article_parser/Extractor.py
article_parser/__init__.py
article_parser-1.8.0.dist-info/LICENSE
article_parser-1.8.0.dist-info/METADATA
article_parser-1.8.0.dist-info/WHEEL
article_parser-1.8.0.dist-info/top_level.txt
article_parser-1.8.0.dist-info/RECORD
