Metadata-Version: 2.1
Name: article-parser
Version: 1.8.0
Summary: A parser that parses articles from any url or html
Home-page: https://github.com/myifeng/article-parser
Author: myifeng
Author-email: myifengs@gmail.com
Maintainer: myifeng
Maintainer-email: myifengs@gmail.com
License: MIT
Keywords: article news html parser Extract extractor body
Classifier: License :: OSI Approved :: MIT License
Classifier: Operating System :: OS Independent
Classifier: Programming Language :: Python
Classifier: Programming Language :: Python :: 3
Classifier: Programming Language :: Python :: 3.8
Classifier: Programming Language :: Python :: 3.9
Classifier: Programming Language :: Python :: 3.10
Classifier: Programming Language :: Python :: 3.11
Classifier: Programming Language :: Python :: 3.12
Classifier: Programming Language :: Python :: 3 :: Only
Classifier: Programming Language :: Python :: Implementation
Requires-Python: >=3.8
License-File: LICENSE
Requires-Dist: beautifulsoup4 ==4.12.3
Requires-Dist: html2text ==2020.1.16
Requires-Dist: requests ==2.31.0
Requires-Dist: lxml ==5.2.2
